{"type": "FeatureCollection", "features": [{"type": "Feature", "geometry": {"type": "Point", "coordinates": [106.8486027, -6.206253]}, "properties": {"type": "hospital", "name": "RSIA Tambak"}}, {"type": "Feature", "geometry": {"type": "Point", "coordinates": [106.8675387, -6.2078757]}, "properties": {"type": "hospital", "name": "Klinik SouthernUK"}}, {"type": "Feature", "geometry": {"type": "Point", "coordinates": [106.8442225, -6.1823419]}, "properties": {"type": "hospital", "name": "Puskesmas Kecamatan Senen Kramat Baru"}}, {"type": "Feature", "geometry": {"type": "Point", "coordinates": [106.8554624, -6.2282877]}, "properties": {"type": "hospital", "name": "Ocean Dental Tebet"}}, {"type": "Feature", "geometry": {"type": "Point", "coordinates": [106.838375, -6.1869354]}, "properties": {"type": "hospital", "name": "RS MENTENG MITRA AFIA"}}, {"type": "Feature", "geometry": {"type": "Point", "coordinates": [106.8723994, -6.184668]}, "properties": {"type": "hospital", "name": "RSUD CEMPAKA PUTIH"}}, {"type": "Feature", "geometry": {"type": "Point", "coordinates": [106.8504657, -6.1818356]}, "properties": {"type": "hospital", "name": "RSUD JOHOR BARU"}}, {"type": "Feature", "geometry": {"type": "Point", "coordinates": [106.8419064, -6.1914003]}, "properties": {"type": "hospital", "name": "RS PRIMAYA PGI CIKINI"}}, {"type": "Feature", "geometry": {"type": "Point", "coordinates": [106.8293431, -6.1898118]}, "properties": {"type": "hospital", "name": "RSUD ABDI WALUYO"}}, {"type": "Feature", "geometry": {"type": "Point", "coordinates": [106.8598631, -6.1935611]}, "properties": {"type": "hospital", "name": "RS PRIMAYA EVASARI"}}, {"type": "Feature", "geometry": {"type": "Point", "coordinates": [106.8517604, -6.1958347]}, "properties": {"type": "hospital", "name": "RS ST. CAROLUS"}}, {"type": "Feature", "geometry": {"type": "Point", "coordinates": [106.8520454, -6.1936527]}, "properties": {"type": "hospital", "name": "RS RADJAK SALEMBA"}}, {"type": "Feature", "geometry": {"type": "Point", "coordinates": [106.8439659, -6.1856105]}, "properties": {"type": "hospital", "name": "RS KRAMAT 128"}}, {"type": "Feature", "geometry": {"type": "Point", "coordinates": [106.8193331, -6.2095279]}, "properties": {"type": "hospital", "name": "RS MURNI TEGUH SUDIRMAN JAKARTA"}}, {"type": "Feature", "geometry": {"type": "Point", "coordinates": [106.8466802, -6.2316371]}, "properties": {"type": "hospital", "name": "RSUD TEBET"}}, {"type": "Feature", "geometry": {"type": "Point", "coordinates": [106.8324591, -6.2199712]}, "properties": {"type": "hospital", "name": "RS METROPOLITAN MEDICAL CENTER (MMC) JAKARTA"}}, {"type": "Feature", "geometry": {"type": "Point", "coordinates": [106.8480329, -6.2245705]}, "properties": {"type": "hospital", "name": "RS BRAWIJAYA SAHARJO"}}, {"type": "Feature", "geometry": {"type": "Point", "coordinates": [106.8463579, -6.2091793]}, "properties": {"type": "hospital", "name": "RS AGUNG"}}, {"type": "Feature", "geometry": {"type": "Point", "coordinates": [106.8660138, -6.2062623]}, "properties": {"type": "hospital", "name": "RSUD MATRAMAN"}}, {"type": "Feature", "geometry": {"type": "Point", "coordinates": [106.8644361, -6.2215235]}, "properties": {"type": "hospital", "name": "RS HERMINA JATINEGARA"}}, {"type": "Feature", "geometry": {"type": "Point", "coordinates": [106.83245220577746, -6.219973786725023]}, "properties": {"type": "hospital", "name": "RS MCC"}}, {"type": "Feature", "geometry": {"type": "Point", "coordinates": [106.86697609999999, -6.2306520999999995]}, "properties": {"type": "hospital", "name": "Rumah Sakit Bersalin Bidara Mulia"}}, {"type": "Feature", "geometry": {"type": "Point", "coordinates": [106.85171290788506, -6.198110689757922]}, "properties": {"type": "hospital", "name": "RSKB Medika"}}, {"type": "Feature", "geometry": {"type": "Point", "coordinates": [106.83241342453115, -6.219922140865757]}, "properties": {"type": "hospital", "name": "Rumah Sakit MMC"}}, {"type": "Feature", "geometry": {"type": "Point", "coordinates": [106.81951584461873, -6.209462833804119]}, "properties": {"type": "hospital", "name": "RS Murni Teguh Sudirman Jakarta"}}, {"type": "Feature", "geometry": {"type": "Point", "coordinates": [106.85209264050732, -6.19365430520643]}, "properties": {"type": "hospital", "name": "Rumah Sakit Radjak Salemba"}}, {"type": "Feature", "geometry": {"type": "Point", "coordinates": [106.84725906860601, -6.201921569372935]}, "properties": {"type": "hospital", "name": "Rumah Sakit Khusus THT dan Bedah Kepala Leher Proklamasi"}}, {"type": "Feature", "geometry": {"type": "Point", "coordinates": [106.85976326317288, -6.1935369487752485]}, "properties": {"type": "hospital", "name": "Evasari Rumah Sakit Awal BROS Group"}}, {"type": "Feature", "geometry": {"type": "Point", "coordinates": [106.87240737543434, -6.184667462358284]}, "properties": {"type": "hospital", "name": "Rumah Sakit Umum Kecamatan Cempaka Putih"}}, {"type": "Feature", "geometry": {"type": "Point", "coordinates": [106.86882248814443, -6.221651032266]}, "properties": {"type": "hospital", "name": "RS Premier Jatinegara"}}, {"type": "Feature", "geometry": {"type": "Point", "coordinates": [106.83407633422848, -6.206209720359019]}, "properties": {"type": "hospital", "name": "Rumah Sakit Khusus Bedah Halimun"}}, {"type": "Feature", "geometry": {"type": "Point", "coordinates": [106.83513856325149, -6.210329692223796]}, "properties": {"type": "hospital", "name": "Rumah Bersalin Budi Kemuliaan"}}, {"type": "Feature", "geometry": {"type": "Point", "coordinates": [106.8466818, -6.2316306]}, "properties": {"type": "hospital", "name": "Rumah Sakit Umum Kecamatan Tebet"}}, {"type": "Feature", "geometry": {"type": "Point", "coordinates": [106.83187243685471, -6.2185186159460475]}, "properties": {"type": "hospital", "name": "Rumah Sakit Mayapada Kuningan"}}, {"type": "Feature", "geometry": {"type": "Point", "coordinates": [106.85538077774869, -6.200176970914969]}, "properties": {"type": "hospital", "name": "RS Jantung Jakarta"}}, {"type": "Feature", "geometry": {"type": "Point", "coordinates": [106.86474387566231, -6.22121215977527]}, "properties": {"type": "hospital", "name": "RS Hermina Jatinegara"}}, {"type": "Feature", "geometry": {"type": "Point", "coordinates": [106.83752800011457, -6.199188569656437]}, "properties": {"type": "hospital", "name": "Rumah Sakit Bedah Bina Estetika"}}, {"type": "Feature", "geometry": {"type": "Point", "coordinates": [106.83683493919993, -6.198600577922679]}, "properties": {"type": "hospital", "name": "Rumah Sakit Mata JEC"}}, {"type": "Feature", "geometry": {"type": "Point", "coordinates": [106.84842540809021, -6.206413247402205]}, "properties": {"type": "hospital", "name": "RSIA Tambak"}}, {"type": "Feature", "geometry": {"type": "Point", "coordinates": [106.84688255865505, -6.202037745881221]}, "properties": {"type": "hospital", "name": "RS K"}}, {"type": "Feature", "geometry": {"type": "Point", "coordinates": [106.8371645143753, -6.195964886045427]}, "properties": {"type": "hospital", "name": "RSU Bunda Jakarta"}}, {"type": "Feature", "geometry": {"type": "Point", "coordinates": [106.82785370663889, -6.191314914222272]}, "properties": {"type": "hospital", "name": "Rumah Sakit YPK Mandiri"}}, {"type": "Feature", "geometry": {"type": "Point", "coordinates": [106.82934682728192, -6.189810753218416]}, "properties": {"type": "hospital", "name": "Rumah Sakit Abdi Waluyo"}}, {"type": "Feature", "geometry": {"type": "Point", "coordinates": [106.85047067861159, -6.181830687843353]}, "properties": {"type": "hospital", "name": "RSUD Johar Baru"}}, {"type": "Feature", "geometry": {"type": "Point", "coordinates": [106.83841391419236, -6.186876459802365]}, "properties": {"type": "hospital", "name": "Rumah Sakit Menteng Mitra Afia"}}, {"type": "Feature", "geometry": {"type": "Point", "coordinates": [106.83192763954435, -6.200801229613402]}, "properties": {"type": "hospital", "name": "Rumah Sehat Sunda Kelapa"}}, {"type": "Feature", "geometry": {"type": "Point", "coordinates": [106.84494391629964, -6.218953969543094]}, "properties": {"type": "hospital", "name": "Rumah Sakit Ibu dan Anak Budhi Jaya"}}, {"type": "Feature", "geometry": {"type": "Point", "coordinates": [106.84190524671581, -6.191407702228906]}, "properties": {"type": "hospital", "name": "Rumah Sakit PGI CIKINI"}}, {"type": "Feature", "geometry": {"type": "Point", "coordinates": [106.86601677025185, -6.2062439413812065]}, "properties": {"type": "hospital", "name": "RSUD Matraman"}}, {"type": "Feature", "geometry": {"type": "Point", "coordinates": [106.8447027281044, -6.19737259152234]}, "properties": {"type": "hospital", "name": "RSCM Unit Pelayanan Mata"}}, {"type": "Feature", "geometry": {"type": "Point", "coordinates": [106.85141290138127, -6.19547755130454]}, "properties": {"type": "hospital", "name": "Rumah Sakit St. Carolus"}}, {"type": "Feature", "geometry": {"type": "Point", "coordinates": [106.84863242958475, -6.194344792089387]}, "properties": {"type": "hospital", "name": "RSKGM - FKG UI"}}, {"type": "Feature", "geometry": {"type": "Point", "coordinates": [106.84685528983101, -6.197008814778132]}, "properties": {"type": "hospital", "name": "Rumah Sakit Cipto Mangunkusumo"}}, {"type": "Feature", "geometry": {"type": "Point", "coordinates": [106.84422163897835, -6.18233755809783]}, "properties": {"type": "hospital", "name": "Puskesmas Kecamatan Senen Kramat Baru"}}, {"type": "Feature", "geometry": {"type": "Point", "coordinates": [106.84402488673962, -6.185574832273563]}, "properties": {"type": "hospital", "name": "Rumah Sakit Kramat 128"}}, {"type": "Feature", "geometry": {"type": "Point", "coordinates": [106.83635443495014, -6.196101977209615]}, "properties": {"type": "hospital", "name": "RSIA Bunda Jakarta"}}, {"type": "Feature", "geometry": {"type": "Point", "coordinates": [106.84637943093647, -6.209221410017587]}, "properties": {"type": "hospital", "name": "RS Agung"}}, {"type": "Feature", "geometry": {"type": "Point", "coordinates": [106.82859497820635, -6.188914363086472]}, "properties": {"type": "hospital", "name": "nan"}}, {"type": "Feature", "geometry": {"type": "Point", "coordinates": [106.84808513893081, -6.224576937350051]}, "properties": {"type": "hospital", "name": "RSIA Brawijaya Saharjo"}}, {"type": "Feature", "geometry": {"type": "Point", "coordinates": [106.83189479540403, -6.2185327105408055]}, "properties": {"type": "hospital", "name": "RS Mayapada Kuningan"}}]}